odoo/addons/stock_barcodes_gs1/README.rst
odoo/addons/stock_barcodes_gs1/__init__.py
odoo/addons/stock_barcodes_gs1/__manifest__.py
odoo/addons/stock_barcodes_gs1/i18n/ca.po
odoo/addons/stock_barcodes_gs1/i18n/es.po
odoo/addons/stock_barcodes_gs1/i18n/stock_barcodes_gs1.pot
odoo/addons/stock_barcodes_gs1/models/__init__.py
odoo/addons/stock_barcodes_gs1/models/barcode_nomenclature.py
odoo/addons/stock_barcodes_gs1/models/barcode_rule.py
odoo/addons/stock_barcodes_gs1/readme/CONTRIBUTORS.rst
odoo/addons/stock_barcodes_gs1/readme/DESCRIPTION.rst
odoo/addons/stock_barcodes_gs1/readme/USAGE.rst
odoo/addons/stock_barcodes_gs1/static/description/icon.png
odoo/addons/stock_barcodes_gs1/static/description/index.html
odoo/addons/stock_barcodes_gs1/tests/__init__.py
odoo/addons/stock_barcodes_gs1/tests/test_stock_barcodes_gs1.py
odoo/addons/stock_barcodes_gs1/views/barcodes_view.xml
odoo/addons/stock_barcodes_gs1/wizard/__init__.py
odoo/addons/stock_barcodes_gs1/wizard/stock_barcodes_read.py
odoo_addon_stock_barcodes_gs1-15.0.3.1.2.dist-info/METADATA
odoo_addon_stock_barcodes_gs1-15.0.3.1.2.dist-info/WHEEL
odoo_addon_stock_barcodes_gs1-15.0.3.1.2.dist-info/top_level.txt
odoo_addon_stock_barcodes_gs1-15.0.3.1.2.dist-info/RECORD
