Metadata-Version: 2.1
Name: odoo-addon-stock_barcodes_gs1
Version: 15.0.3.1.2
Summary: It provides read GS1 barcode on stock operations.
Home-page: https://github.com/OCA/stock-logistics-barcode
Author: Tecnativa, Odoo Community Association (OCA)
Author-email: support@odoo-community.org
License: AGPL-3
Classifier: Programming Language :: Python
Classifier: Framework :: Odoo
Classifier: Framework :: Odoo :: 15.0
Classifier: License :: OSI Approved :: GNU Affero General Public License v3
Requires-Python: >=3.8
Requires-Dist: odoo-addon-stock-barcodes<15.1dev,>=15.0dev
Requires-Dist: odoo<15.1dev,>=15.0a
